{
  "title": "Опросник для обучающихся по выявлению информированности о рисках вовлечения в деструктивную деятельность",
  "questions": [
    {
      "number": 1,
      "question": "Насколько ты уверен в своей способности распознать попытку вербовки в запрещенные группировки?",
      "options": [
        "А) Абсолютно уверен, знаю конкретные признаки",
        "Б) Скорее уверен, но до конца понимаю методы вербовщиков",
        "В) Затрудняюсь ответить, никогда не задумывался об этом",
        "Г) Не считаю это важным для себя"
      ]
    },
    {
      "number": 2,
      "question": "Как ты поступишь, если незнакомец в интернете предложит тебе участие в 'особой миссии' с оплатой?",
      "options": [
        "А) Немедленно заблокирую и сообщу администрации платформы",
        "Б) Попробую выяснить, чтобы понять, о чем речь",
        "В) Соглашусь, если предложение покажется интересным",
        "Г) Посоветуюсь с родителями, чтобы посоветоваться"
      ]
    },
    {
      "number": 3,
      "question": "Что ты считаешь наиболее опасным в социальных сетях?",
      "options": [
        "А) Группы с экстремистским контентом",
        "Б) Распространение личной информации",
        "В) Возможное быстрое общение и манипуляции",
        "Г) Ничего, ведь я веду себя осторожно"
      ]
    },
    {
      "number": 4,
      "question": "Как ты отреагируешь на предложение вступить в закрытую группу 'для избранных'?",
      "options": [
        "А) Отклоню без раздумий",
        "Б) Сначала отыщу информацию о группе",
        "В) Приму приглашение из любопытства",
        "Г) Посоветуюсь с родителями или тренером"
      ]
    },
    {
      "number": 5,
      "question": "Что может свидетельствовать о попытке психологического давления?",
      "options": [
        "А) Требование сохранять общение в тайне",
        "Б) Постоянные комплименты и подарки",
        "В) Критика твоего круга общения",
        "Г) Все вышеперечисленное"
      ]
    },
    {
      "number": 6,
      "question": "Куда ты обратишься при подозрении на вербовку одноклассника?",
      "options": [
        "А) К родителям и тренеру",
        "Б) В правоохранительные органы",
        "В) Постараюсь разобраться сам",
        "Г) Ничего, это не мое дело"
      ]
    },
    {
      "number": 7,
      "question": "Как ты оцениваешь свою уязвимость к манипуляциям?",
      "options": [
        "А) Я хорошо защищен знаниями и критическим мышлением",
        "Б) Иногда поддаюсь эмоциональному воздействию",
        "В) Часто принимаю решения под влиянием других",
        "Г) Не задумывался об этом"
      ]
    },
    {
      "number": 8,
      "question": "Что является признаком деструктивного контента?",
      "options": [
        "А) Призывы к насилию и ненависти",
        "Б) Обещания легких решений сложных проблем",
        "В) Требование разрыва семейных связей",
        "Г) Все варианты верны"
      ]
    },
    {
      "number": 9,
      "question": "Как ты поступаешь с личной информацией в интернете?",
      "options": [
        "А) Максимально ограничиваю её распространение",
        "Б) Делюсь только с проверенными друзьями",
        "В) Публикую открыто, мне нечего скрывать",
        "Г) Не слежу за этим"
      ]
    },
    {
      "number": 10,
      "question": "Что ты посоветуешь другу при подозрении на вербовку?",
      "options": [
        "А) Немедленно обратиться за помощью",
        "Б) Разорвать контакты с подозрительными личностями",
        "В) Собрать доказательства для обращения в полицию",
        "Г) Сам не знаю, что посоветовать"
      ]
    }
  ],
  "notes": {
    "methodical_recommendations": [
      "Проведение анонимно с гарантией конфиденциальности",
      "Анализ результатов в обобщенном виде",
      "Организация занятий по проблемным вопросам",
      "Опрос проводится не для сбора официальной статистики, а для анализа общего положения и корректировки профилактических мероприятий"
    ],
    "result_interpretation": [
      "Ответы А и Б свидетельствуют о сформированной критической позиции",
      "Ответы В и Г указывают на необходимость дополнительной профилактической работы",
      "Особое внимание уделить вопросам 11, 13, 15, 16, 18",
      "Результаты использовать для корректировки программ профилактики"
    ]
  }
}
